<annotation>
	<folder>train_augmented</folder>
	<filename>300.jpg</filename>
	<path>/home/vincent/Documents/INSA/5A/Projet_SIEC/Road-Analysis-Project/machineLearning_model/training_search/images/train_augmented/300.jpg</path>
	<source>
		<database>Unknown</database>
	</source>
	<size>
		<width>1640</width>
		<height>922</height>
		<depth>3</depth>
	</size>
	<segmented>0</segmented>
	<object>
		<name>medium</name>
		<pose>Unspecified</pose>
		<truncated>0</truncated>
		<difficult>0</difficult>
		<bndbox>
			<xmin>935</xmin>
			<ymin>603</ymin>
			<xmax>1047</xmax>
			<ymax>723</ymax>
		</bndbox>
	</object>
	<object>
		<name>big</name>
		<pose>Unspecified</pose>
		<truncated>0</truncated>
		<difficult>0</difficult>
		<bndbox>
			<xmin>874</xmin>
			<ymin>275</ymin>
			<xmax>1020</xmax>
			<ymax>381</ymax>
		</bndbox>
	</object>
</annotation>
