<annotation>
	<folder>dataset_original</folder>
	<filename>77.jpg</filename>
	<path>/home/vincent/Documents/Travail/INSA_T/5e_annee/ProjetSIEC/github/Road-Analysis-Project/Housemade_machineLearning_Model/dataset_original/77.jpg</path>
	<source>
		<database>Unknown</database>
	</source>
	<size>
		<width>1640</width>
		<height>922</height>
		<depth>3</depth>
	</size>
	<segmented>0</segmented>
	<object>
		<name>prohibited</name>
		<pose>Unspecified</pose>
		<truncated>0</truncated>
		<difficult>0</difficult>
		<bndbox>
			<xmin>914</xmin>
			<ymin>563</ymin>
			<xmax>954</xmax>
			<ymax>603</ymax>
		</bndbox>
	</object>
</annotation>
