<annotation>
	<folder>augmented_data</folder>
	<filename>650.jpg</filename>
	<path>/home/vincent/Documents/Travail/INSA_T/5e_annee/ProjetSIEC/github/Road-Analysis-Project/machineLearning_model/training_search/images/train/augmented_data/650.jpg</path>
	<source>
		<database>Unknown</database>
	</source>
	<size>
		<width>300</width>
		<height>300</height>
		<depth>3</depth>
	</size>
	<segmented>0</segmented>
	<object>
		<name>small</name>
		<pose>Unspecified</pose>
		<truncated>1</truncated>
		<difficult>0</difficult>
		<bndbox>
			<xmin>234</xmin>
			<ymin>253</ymin>
			<xmax>283</xmax>
			<ymax>300</ymax>
		</bndbox>
	</object>
	<object>
		<name>medium</name>
		<pose>Unspecified</pose>
		<truncated>0</truncated>
		<difficult>0</difficult>
		<bndbox>
			<xmin>13</xmin>
			<ymin>180</ymin>
			<xmax>137</xmax>
			<ymax>262</ymax>
		</bndbox>
	</object>
</annotation>
